varsnap/__init__.py
varsnap/__version__.py
varsnap/assert_generator.py
varsnap/core.py
varsnap/py.typed
varsnap-1.5.9.dist-info/METADATA
varsnap-1.5.9.dist-info/WHEEL
varsnap-1.5.9.dist-info/top_level.txt
varsnap-1.5.9.dist-info/RECORD
