Metadata-Version: 2.4
Name: varsnap
Version: 1.5.9
Summary: Varsnap
Author-email: Varsnap <admin@varsnap.com>
License-Expression: MIT
Project-URL: Homepage, https://www.varsnap.com/
Keywords: testing
Classifier: Development Status :: 4 - Beta
Classifier: Intended Audience :: Developers
Classifier: Natural Language :: English
Classifier: Topic :: Software Development
Classifier: Programming Language :: Python :: 3
Classifier: Programming Language :: Python :: 3.7
Classifier: Programming Language :: Python :: 3.8
Classifier: Programming Language :: Python :: 3.9
Classifier: Programming Language :: Python :: 3.10
Classifier: Programming Language :: Python :: 3.11
Classifier: Programming Language :: Python :: 3.12
Classifier: Programming Language :: Python :: 3.13
Classifier: Programming Language :: Python :: 3.14
Classifier: Typing :: Typed
Requires-Python: >=3.7
Requires-Dist: dill<0.5.0,>=0.4.0
Requires-Dist: requests<3.0,>=2.0
Provides-Extra: test
Requires-Dist: coverage==7.11.0; extra == "test"
Requires-Dist: ruff==0.14.1; extra == "test"
Requires-Dist: mypy==1.18.2; extra == "test"
Requires-Dist: types-requests==2.32.4.20250913; extra == "test"
